[
  {
    "id": "1771507375301",
    "name": "Ama Keyla",
    "memo": "",
    "study": false
  },
  {
    "id": "1771507381516",
    "name": "Ama Ote Harefa",
    "memo": "",
    "study": false
  },
  {
    "id": "1771507386296",
    "name": "Johan",
    "memo": "",
    "study": false
  },
  {
    "id": "1771507397167",
    "name": "Ojak Sihombing",
    "memo": "",
    "study": true
  },
  {
    "id": "1771507403588",
    "name": "Roy",
    "memo": "",
    "study": false
  },
  {
    "id": "1771507408625",
    "name": "Stefanus",
    "memo": "",
    "study": false
  },
  {
    "id": "1771507412309",
    "name": "Toyo",
    "memo": "",
    "study": false
  },
  {
    "id": "1771756060164",
    "name": "Ama Jiel",
    "memo": "",
    "study": false
  }
]